[
    {
        "title": "Cats",
        "slug": "cats",
        "img": "actionimg/cats.png",
        "game": "https://bitlifeonline.github.io/class12523/cats/",
        "domain": 20,
        "date": 12523,
        "cat": "action-games-unblocked"
    },
    {
        "title": "Death Chase",
        "slug": "death-chase",
        "img": "actionimg/death-chase.png",
        "game": "https://bitlifeonline.github.io/class12523/death-chase/",
        "domain": 20,
        "date": 12523,
        "cat": "action-games-unblocked"
    },
    {
        "title": "Death Chase 2",
        "slug": "death-chase-2",
        "img": "actionimg/death-chase-2.png",
        "game": "https://bitlifeonline.github.io/class12523/death-chase-2/",
        "domain": 20,
        "date": 12523,
        "cat": "action-games-unblocked"
    },
    {
        "title": "Eugenes Life",
        "slug": "eugenes-life",
        "img": "actionimg/eugenes-life.png",
        "game": "https://bitlifeonline.github.io/class12523/eugenes-life/",
        "domain": 20,
        "date": 12523,
        "cat": "action-games-unblocked"
    },
    {
        "title": "Lucky Life",
        "slug": "lucky-life",
        "img": "actionimg/lucky-life.png",
        "game": "https://bitlifeonline.github.io/class12523/lucky-life/",
        "domain": 20,
        "date": 12523,
        "cat": "action-games-unblocked"
    },
    {
        "title": "sharkosaurus",
        "slug": "sharkosaurus-rampage",
        "img": "actionimg/sharkosaurus-rampage.png",
        "game": "https://bitlifeonline.github.io/class12523/sharkosaurus-rampage/",
        "domain": 20,
        "date": 12523,
        "cat": "action-games-unblocked"
    },
    {
        "title": "Short Life",
        "slug": "short-life",
        "img": "actionimg/short-life.png",
        "game": "https://bitlifeonline.github.io/class12523/short-life/",
        "domain": 20,
        "date": 12523,
        "cat": "action-games-unblocked"
    },
    {
        "title": "Short Life 2",
        "slug": "short-life-2",
        "img": "actionimg/short-life-2.png",
        "game": "https://bitlifeonline.github.io/class12523/short-life-2/",
        "domain": 20,
        "date": 12523,
        "cat": "action-games-unblocked"
    },
    {
        "title": "Swingo",
        "slug": "swingo",
        "img": "actionimg/swingo.png",
        "game": "https://bitlifeonline.github.io/class12523/swingo/",
        "domain": 20,
        "date": 12523,
        "cat": "action-games-unblocked"
    },
    {
        "slug": "jacksmith",
        "title": "Jacksmith",
        "cat": "action-games-unblocked",
        "domain": 26,
        "img": "https://slope-game.github.io/new5923/jacksmith.png"
    },
    {
        "slug": "iron-snout",
        "title": "Iron Snout",
        "cat": "action-games-unblocked",
        "domain": 1
    },
    {
        "slug": "iron-snout-2",
        "title": "Iron Snout 2",
        "cat": "action-games-unblocked",
        "domain": 1
    },
    {
        "title": "War of Sticks",
        "slug": "war-of-sticks",
        "img": "actionimg/war-of-sticks.png",
        "game": "https://bitlifeonline.github.io/class12523/war-of-sicks/",
        "domain": 20,
        "date": 12523,
        "cat": "action-games-unblocked"
    },
    {
        "title": "Hunter Assasin 2",
        "slug": "hunter-assassin-2",
        "img": "actionimg/hunter-assassin-2.png",
        "game": "https://ClassroomJq.github.io/class276223/hunter-assassin-2/",
        "domain": 20,
        "date": 12523,
        "cat": "action-games-unblocked"
    },
    {
        "slug": "johnny-upgrade",
        "title": "Johnny Upgrade",
        "domain": 22,
        "img": "https://slope-game.github.io/new3623/johnny-upgrade/logo.png",
        "cat": "action-games-unblocked"
    },
    {
        "slug": "among-us",
        "title": "Among us",
        "cat": "action-games-unblocked",
        "domain": 1
    },
    {
        "slug": "magikmon",
        "title": "Magikmon",
        "cat": "action-games-unblocked",
        "domain": 1
    },
    {
        "slug": "microwars",
        "title": "Microwars",
        "cat": "action-games-unblocked",
        "domain": 4
    },
    {
        "slug": "thumb-fighter",
        "title": "Thumb fighter",
        "cat": "action-games-unblocked",
        "domain": 3
    },{
        "slug": "stickman-fighter-epic-battle",
        "title": "Stickman Fighter",
        "cat": "action-games-unblocked",
        "domain": 1
    },
    {
        "slug": "stickman-fighter-epic-battle-2",
        "title": "Stickman Fighter 2",
        "cat": "action-games-unblocked",
        "domain": 1
    },
    {
        "slug": "temple-of-boom",
        "title": "Temple of boom",
        "cat": "action-games-unblocked",
        "domain": 4
    }
]